seismostats/__init__.py
seismostats/analysis/__init__.py
seismostats/analysis/b_significant.py
seismostats/analysis/estimate_mc.py
seismostats/analysis/lilliefors.py
seismostats/analysis/magnitudes.py
seismostats/analysis/avalue/__init__.py
seismostats/analysis/avalue/base.py
seismostats/analysis/avalue/classic.py
seismostats/analysis/avalue/more_positive.py
seismostats/analysis/avalue/positive.py
seismostats/analysis/avalue/tests/__init__.py
seismostats/analysis/avalue/tests/test_avalue.py
seismostats/analysis/avalue/tests/test_base.py
seismostats/analysis/bvalue/__init__.py
seismostats/analysis/bvalue/base.py
seismostats/analysis/bvalue/classic.py
seismostats/analysis/bvalue/kijko_smit.py
seismostats/analysis/bvalue/more_positive.py
seismostats/analysis/bvalue/positive.py
seismostats/analysis/bvalue/utils.py
seismostats/analysis/bvalue/utsu.py
seismostats/analysis/bvalue/weichert.py
seismostats/analysis/bvalue/tests/__init__.py
seismostats/analysis/bvalue/tests/test_base.py
seismostats/analysis/bvalue/tests/test_bvalues.py
seismostats/analysis/bvalue/tests/test_period_mc.py
seismostats/analysis/bvalue/tests/test_utils.py
seismostats/analysis/bvalue/tests/data/simulated_magnitudes.csv
seismostats/analysis/declustering/__init__.py
seismostats/analysis/declustering/base.py
seismostats/analysis/declustering/dec_gardner_knopoff.py
seismostats/analysis/declustering/distance_time_windows.py
seismostats/analysis/declustering/utils.py
seismostats/analysis/declustering/tests/__init__.py
seismostats/analysis/declustering/tests/dec_gardner_knopoff_test.py
seismostats/analysis/declustering/tests/test_distance_time_windows.py
seismostats/analysis/declustering/tests/utils_test.py
seismostats/analysis/declustering/tests/data/gardner_knopoff_test_catalogue.csv
seismostats/analysis/tests/__init__.py
seismostats/analysis/tests/test_b_significant.py
seismostats/analysis/tests/test_estimate_mc.py
seismostats/analysis/tests/test_lillifors.py
seismostats-1.0.1.dist-info/licenses/LICENSE
seismostats-1.0.1.dist-info/METADATA
seismostats-1.0.1.dist-info/WHEEL
seismostats-1.0.1.dist-info/top_level.txt
seismostats-1.0.1.dist-info/RECORD
