Metadata-Version: 2.4
Name: SeismoStats
Version: 1.0.1
Summary: A Python Package for Statistical Seismology.
License:                     GNU AFFERO GENERAL PUBLIC LICENSE
Project-URL: Documentation, https://seismostats.readthedocs.io/
Project-URL: Repository, https://github.com/swiss-seismological-service/SeismoStats
Project-URL: Issues, https://github.com/swiss-seismological-service/SeismoStats/issues
Keywords: seismology,statistics,earthquake
Classifier: Development Status :: 4 - Beta
Classifier: Environment :: Console
Classifier: Intended Audience :: Science/Research
Classifier: Intended Audience :: Education
Classifier: Operating System :: OS Independent
Classifier: License :: OSI Approved :: GNU Affero General Public License v3
Classifier: Programming Language :: Python :: 3
Classifier: Programming Language :: Python :: 3.10
Classifier: Programming Language :: Python :: 3.12
Classifier: Topic :: Scientific/Engineering
Classifier: Topic :: Scientific/Engineering :: Physics
Requires-Python: >=3.10
License-File: LICENSE
Requires-Dist: cartopy
Requires-Dist: geopandas
Requires-Dist: jinja2
Requires-Dist: matplotlib
Requires-Dist: numpy
Requires-Dist: pandas
Requires-Dist: requests
Requires-Dist: scipy
Requires-Dist: shapely
Requires-Dist: typing_extensions
Requires-Dist: statsmodels
Provides-Extra: dev
Requires-Dist: build; extra == "dev"
Requires-Dist: docutils==0.19; extra == "dev"
Requires-Dist: flake8; extra == "dev"
Requires-Dist: isort; extra == "dev"
Requires-Dist: myst-parser; extra == "dev"
Requires-Dist: nbsphinx-link; extra == "dev"
Requires-Dist: nbsphinx; extra == "dev"
Requires-Dist: pandoc; extra == "dev"
Requires-Dist: pydata-sphinx-theme; extra == "dev"
Requires-Dist: pytest-cov; extra == "dev"
Requires-Dist: pytest; extra == "dev"
Requires-Dist: responses; extra == "dev"
Requires-Dist: setuptools-scm; extra == "dev"
Requires-Dist: sphinx-autobuild; extra == "dev"
Requires-Dist: sphinx; extra == "dev"
Requires-Dist: tox; extra == "dev"
Requires-Dist: twine; extra == "dev"
Provides-Extra: openquake
Requires-Dist: openquake-engine; extra == "openquake"
Requires-Dist: numpy<2; extra == "openquake"
Requires-Dist: fiona; extra == "openquake"
Provides-Extra: jupyter
Requires-Dist: notebook; extra == "jupyter"
Dynamic: license-file
